{
  "title": "Schema",
  "navigationTitle": "",
  "body": [
    {
      "type": "paragraph",
      "textAlign": "left",
      "content": [
        {
          "type": "text",
          "text": "A schema is a collection of "
        },
        {
          "type": "text",
          "text": "Types",
          "marks": [
            {
              "type": "link",
              "attrs": {
                "data-id": "L5f7XuNlknTxxICB7sxMu",
                "data-entry": "267QuOShP41WnFxQFOcHZQoCsla",
                "data-type": null,
                "href": null,
                "title": null
              }
            }
          ]
        },
        {
          "type": "text",
          "text": "."
        }
      ]
    },
    {
      "id": "267QjRgoDq3nZ6Dth0o3MElJgzP",
      "type": "CodeBlock",
      "code": "import {Config} from 'alinea'\n\nConfig.schema({\n  types: {\n    TypeA, TypeB, TypeC\n  }\n})",
      "fileName": "",
      "language": "",
      "compact": false
    },
    {
      "type": "heading",
      "level": 2,
      "textAlign": "left",
      "content": [
        {
          "type": "text",
          "text": "Configuration"
        }
      ]
    },
    {
      "type": "paragraph",
      "textAlign": "left",
      "content": [
        {
          "type": "text",
          "text": "Your Schema should be defined in the "
        },
        {
          "type": "text",
          "text": "CMS config",
          "marks": [
            {
              "type": "link",
              "attrs": {
                "data-id": "2aAxVMSAONngMXzsR2poLuRALIY",
                "data-entry": "259Ey7LXgqL7ZDGJ8XK1vBJmZrh",
                "data-type": "entry",
                "href": null,
                "title": ""
              }
            }
          ]
        },
        {
          "type": "text",
          "text": ". There are currently no configuration options for it."
        }
      ]
    },
    {
      "type": "heading",
      "textAlign": "left",
      "level": 2,
      "content": [
        {
          "type": "text",
          "text": "Example schema"
        }
      ]
    },
    {
      "type": "paragraph",
      "textAlign": "left",
      "content": [
        {
          "type": "text",
          "text": "The Schema below is a minimal example of a blog setup. It holds two types: `BlogOverview` and `BlogPost`. The overview type corresponds to a page that lists the posts. To achieve that it is configured as a container which can hold blog posts as children."
        }
      ]
    },
    {
      "id": "286gbW4zHgdrAHcGBLGRtixZguV",
      "type": "CodeBlock",
      "code": "import {Config, Field} from 'alinea'\n\nConfig.schema({\n  types: {\n    BlogOverview: Config.document('Blog overview', {\n      contains: ['BlogPost']\n    }),\n    BlogPost: Config.document('Blog post', {\n      publishDate: Field.date('Publish date'),\n      body: Field.richText('Body')\n    })\n  }\n})",
      "fileName": "",
      "language": "",
      "compact": false
    }
  ],
  "metadata": {
    "title": "",
    "description": "",
    "openGraph": {
      "title": "",
      "image": {},
      "description": ""
    }
  },
  "@alinea": {
    "entryId": "267KTV8uPHIdZgFUQvJf06sfm4h",
    "type": "Docs",
    "index": "Zwd"
  }
}